falcon_oas/__init__.py
falcon_oas/__version__.py
falcon_oas/exceptions.py
falcon_oas/extensions.py
falcon_oas/factories.py
falcon_oas/middlewares.py
falcon_oas/problems.py
falcon_oas/request.py
falcon_oas/routing.py
falcon_oas/security.py
falcon_oas/utils.py
falcon_oas-0.5.0.dist-info/LICENSE.txt
falcon_oas-0.5.0.dist-info/METADATA
falcon_oas-0.5.0.dist-info/WHEEL
falcon_oas-0.5.0.dist-info/top_level.txt
falcon_oas-0.5.0.dist-info/RECORD
